grid_pathfinding/__init__.py
grid_pathfinding/algorithms/__init__.py
grid_pathfinding/algorithms/astar.py
grid_pathfinding/algorithms/base.py
grid_pathfinding/algorithms/hpastar.py
grid_pathfinding/algorithms/replanning.py
grid_pathfinding/cache/__init__.py
grid_pathfinding/cache/path_cache.py
grid_pathfinding/core/__init__.py
grid_pathfinding/core/grid.py
grid_pathfinding/core/node.py
grid_pathfinding/costs/__init__.py
grid_pathfinding/costs/base.py
grid_pathfinding/costs/congestion.py
grid_pathfinding/heuristics/__init__.py
grid_pathfinding/heuristics/base.py
grid_pathfinding/heuristics/euclidean.py
grid_pathfinding/heuristics/manhattan.py
grid_pathfinding/movement/__init__.py
grid_pathfinding/movement/base.py
grid_pathfinding/movement/cardinal_3d.py
wareflow_grid_pathfinding-0.1.0.dist-info/METADATA
wareflow_grid_pathfinding-0.1.0.dist-info/WHEEL
wareflow_grid_pathfinding-0.1.0.dist-info/RECORD
