Metadata-Version: 2.4
Name: wareflow-grid-pathfinding
Version: 0.1.0
Summary: High-performance 3D grid pathfinding with A* and HPA* algorithms
Requires-Python: >=3.9
Provides-Extra: dev
Requires-Dist: black>=23.0; extra == 'dev'
Requires-Dist: mypy>=1.0; extra == 'dev'
Requires-Dist: pytest-benchmark>=4.0; extra == 'dev'
Requires-Dist: pytest-cov>=4.0; extra == 'dev'
Requires-Dist: pytest>=7.0; extra == 'dev'
Provides-Extra: numpy
Requires-Dist: numpy>=1.20; extra == 'numpy'
